[
    {
        "id": 490,
        "song": "Let it go",
        "difficulty": "medium",
        "category": "guessthesong"
    },
    {
        "id": 491,
        "song": "بلا ولا شي",
        "difficulty": "medium",
        "category": "guessthesong"
    },
    {
        "song": "Je suis malade",
        "id": 492,
        "difficulty": "medium",
        "category": "guessthesong"
    },
    {
        "id": 493,
        "song": "كيفك انت",
        "difficulty": "medium",
        "category": "guessthesong"
    },
    {
        "id": 494,
        "song": "حبيتك بالصيف",
        "difficulty": "medium",
        "category": "guessthesong"
    },
    {
        "id": 495,
        "song": "يا غايب",
        "difficulty": "medium",
        "category": "guessthesong"
    },
    {
        "id": 496,
        "song": "بنط العريض",
        "difficulty": "medium",
        "category": "guessthesong"
    },
    {
        "id": 497,
        "song": "يا حبي اللي غاب",
        "difficulty": "medium",
        "category": "guessthesong"
    },
    {
        "id": 498,
        "song": "حلوة يا بلدي",
        "difficulty": "medium",
        "category": "guessthesong"
    },
    {
        "id": 499,
        "song": "يا عسل",
        "difficulty": "medium",
        "category": "guessthesong"
    },
    {
        "id": 500,
        "song": "على رمش عيونها",
        "difficulty": "medium",
        "category": "guessthesong"
    },
    {
        "id": 501,
        "song": "فوق النخل",
        "difficulty": "medium",
        "category": "guessthesong"
    },
    {
        "id": 502,
        "song": "ابعتلي جواب",
        "difficulty": "medium",
        "category": "guessthesong"
    },
    {
        "id": 503,
        "song": "عتريس",
        "difficulty": "medium",
        "category": "guessthesong"
    },
    {
        "id": 504,
        "song": "قلبي عاليمين",
        "difficulty": "medium",
        "category": "guessthesong"
    },
    {
        "id": 505,
        "song": "عمر عسل",
        "difficulty": "medium",
        "category": "guessthesong"
    },
    {
        "id": 506,
        "song": "يا بتفكر يا بتحس",
        "difficulty": "medium",
        "category": "guessthesong"
    },
    {
      "id": 507,
        "song": "أخدت القرار",
        "difficulty": "medium",
        "category": "guessthesong"
    },
    {
        "id": 508,
        "song": "ضلي ضحكي",
        "difficulty": "medium",
        "category": "guessthesong"
    },
        {
        "id": 509,
        "song": "تركني لحالي",
        "difficulty": "medium",
        "category": "guessthesong"
    },
        {
        "id": 510,
        "song": "يخرب بيتك",
        "difficulty": "medium",
        "category": "guessthesong"
    },
        {
        "id": 511,
        "song": "عم بتعلّق فيك",
        "difficulty": "medium",
        "category": "guessthesong"
    },
        {
        "id": 512,
        "song": "إنتبه على حالك",
        "difficulty": "medium",
        "category": "guessthesong"
    },
        {
        "id": 513,
        "song": "قلبي دق",
        "difficulty": "medium",
        "category": "guessthesong"
    },
        {
        "id": 514,
        "song": "ما في ورد",
        "difficulty": "medium",
        "category": "guessthesong"
    },
        {
        "id": 515,
        "song": "محلاكي",
        "difficulty": "medium",
        "category": "guessthesong"
    },
        {
        "id": 516,
        "song": "نيالك يا هوى",
        "difficulty": "medium",
        "category": "guessthesong"
    },
        {
        "id": 517,
        "song": "مش عم تظبط معي",
        "difficulty": "medium",
        "category": "guessthesong"
    },
        {
        "id": 518,
        "song": "غرفة عمليات",
        "difficulty": "medium",
        "category": "guessthesong"
    },
        {
        "id": 519,
        "song": "باشق مجروح",
        "difficulty": "medium",
        "category": "guessthesong"
    },
        {
        "id": 520,
        "song": "خليك بحالك",
        "difficulty": "medium",
        "category": "guessthesong"
    },
        {
        "id": 521,
        "song": "اعتزلت الغرام",
        "difficulty": "medium",
        "category": "guessthesong"
    },
        {
        "id": 522,
        "song": "لون السما",
        "difficulty": "medium",
        "category": "guessthesong"
    },
        {
        "id": 523,
        "song": "شو أخبارك",
        "difficulty": "medium",
        "category": "guessthesong"
    },
        {
        "id": 524,
        "song": "إدام الكل",
        "difficulty": "medium",
        "category": "guessthesong"
    },
        {
        "id": 525,
        "song": "غلاك",
        "difficulty": "medium",
        "category": "guessthesong"
    },
        {
        "id": 526,
        "song": "صبابين الشاي",
        "difficulty": "medium",
        "category": "guessthesong"
    },
        {
        "id": 527,
        "song": "معرفش ليه",
        "difficulty": "medium",
        "category": "guessthesong"
    },
        {
        "id": 528,
        "song": "أجمل غمرة",
        "difficulty": "medium",
        "category": "guessthesong"
    },
            {
        "id": 529,
        "song": "إيه نعم",
        "difficulty": "medium",
        "category": "guessthesong"
    },
            {
        "id": 530,
        "song": "آه منك يا هوا",
        "difficulty": "medium",
        "category": "guessthesong"
    },
            {
        "id": 531,
        "song": "حب و مكتر",
        "difficulty": "medium",
        "category": "guessthesong"
    },
            {
        "id": 532,
        "song": "صايرله",
        "difficulty": "medium",
        "category": "guessthesong"
    },
            {
        "id": 533,
        "song": "خلصت الحكاية",
        "difficulty": "medium",
        "category": "guessthesong"
    },
            {
        "id": 534,
        "song": "فكرتن خلصوا",
        "difficulty": "medium",
        "category": "guessthesong"
    },
            {
        "id": 535,
        "song": "بتعقدي",
        "difficulty": "medium",
        "category": "guessthesong"
    },
            {
        "id": 536,
        "song": "بوستك",
        "difficulty": "medium",
        "category": "guessthesong"
    },
            {
        "id": 537,
        "song": "بالعربي",
        "difficulty": "medium",
        "category": "guessthesong"
    },
            {
        "id": 538,
        "song": "نسينى الدنيا",
        "difficulty": "medium",
        "category": "guessthesong"
    },
            {
        "id": 539,
        "song": "انت ايه",
        "difficulty": "medium",
        "category": "guessthesong"
    },
            {
        "id": 540,
        "song": "لا تنحني",
        "difficulty": "medium",
        "category": "guessthesong"
    },
            {
        "id": 541,
        "song": "شو سهل الحكي",
        "difficulty": "medium",
        "category": "guessthesong"
    },
            {
        "id": 542,
        "song": "قال جانى بعد يومين",
        "difficulty": "medium",
        "category": "guessthesong"
    },
            {
        "id": 542,
        "song": "مش بالكلام",
        "difficulty": "medium",
        "category": "guessthesong"
    },
            {
        "id": 543,
        "song": "بتعرف شعور",
        "difficulty": "medium",
        "category": "guessthesong"
    },
            {
        "id": 544,
        "song": "قلبي يا قلبي",
        "difficulty": "medium",
        "category": "guessthesong"
    },
            {
        "id": 545,
        "song": "لمسة إيد",
        "difficulty": "medium",
        "category": "guessthesong"
    },
            {
        "id": 546,
        "song": "خلص الدمع",
        "difficulty": "medium",
        "category": "guessthesong"
    },
            {
        "id": 547,
        "song": "لا تشكي فيي",
        "difficulty": "medium",
        "category": "guessthesong"
    },
            {
        "id": 548,
        "song": "الحب الأولاني",
        "difficulty": "medium",
        "category": "guessthesong"
    },
            {
        "id": 549,
        "song": "إلا إنت",
        "difficulty": "medium",
        "category": "guessthesong"
    },
            {
        "id": 550,
        "song": "كان صديقي",
        "difficulty": "medium",
        "category": "guessthesong"
    },
            {
        "id": 551,
        "song": "يا ريتك مرتي",
        "difficulty": "medium",
        "category": "guessthesong"
    },
            {
        "id": 552,
        "song": "موجوع",
        "difficulty": "medium",
        "category": "guessthesong"
    },
            {
        "id": 553,
        "song": "كل القصايد",
        "difficulty": "medium",
        "category": "guessthesong"
    },
            {
        "id": 554,
        "song": "شو قصة قلبي",
        "difficulty": "medium",
        "category": "guessthesong"
    },
              {
        "id": 555,
        "song": "باب عم يبكي",
        "difficulty": "medium",
        "category": "guessthesong"
    },
           {
        "id": 556,
        "song": "Despacito",
        "difficulty": "medium",
        "category": "guessthesong"
    },
           {
        "id": 557,
        "song": "Someone like you",
        "difficulty": "medium",
        "category": "guessthesong"
    },
           {
        "id": 558,
        "song": "Counting Stars",
        "difficulty": "medium",
        "category": "guessthesong"
    },
           {
        "id": 559,
        "song": "Wind of change",
        "difficulty": "medium",
        "category": "guessthesong"
    },
           {
        "id": 560,
        "song": "On the floor",
        "difficulty": "medium",
        "category": "guessthesong"
    },
           {
        "id": 561,
        "song": "Radioactive",
        "difficulty": "medium",
        "category": "guessthesong"
    },
           {
        "id": 562,
        "song": "Talk Dirty",
        "difficulty": "medium",
        "category": "guessthesong"
    },
           {
        "id": 563,
        "song": "Can't feel my face",
        "difficulty": "medium",
        "category": "guessthesong"
    },
           {
        "id": 564,
        "song": "Single Ladies",
        "difficulty": "medium",
        "category": "guessthesong"
    },
           {
        "id": 565,
        "song": "My immortal",
        "difficulty": "medium",
        "category": "guessthesong"
    },
           {
        "id": 566,
        "song": "Problem",
        "difficulty": "medium",
        "category": "guessthesong"
    },
           {
        "id": 567,
        "song": "Pillowtalk",
        "difficulty": "medium",
        "category": "guessthesong"
    },
           {
        "id": 568,
        "song": "Can't remember to forget you",
        "difficulty": "medium",
        "category": "guessthesong"
    },
           {
        "id": 569,
        "song": "Wrecking ball",
        "difficulty": "medium",
        "category": "guessthesong"
    },
           {
        "id": 570,
        "song": "International Love",
        "difficulty": "medium",
        "category": "guessthesong"
    },
          {
        "id": 571,
        "song": "medium come medium go",
        "difficulty": "medium",
        "category": "guessthesong"
    },

          {
        "id": 572,
        "song": "Hello",
        "difficulty": "medium",
        "category": "guessthesong"
    },

          {
        "id": 573,
        "song": "Roar",
        "difficulty": "medium",
        "category": "guessthesong"
    },

          {
        "id": 574,
        "song": "Sugar",
        "difficulty": "medium",
        "category": "guessthesong"
    },

          {
        "id": 575,
        "song": "Party Rock Anthem",
        "difficulty": "medium",
        "category": "guessthesong"
    },

          {
        "id": 576,
        "song": "Wake me up",
        "difficulty": "medium",
        "category": "guessthesong"
    },

          {
        "id": 577,
        "song": "All of me",
        "difficulty": "medium",
        "category": "guessthesong"
    },

          {
        "id": 578,
        "song": "Call me maybe",
        "difficulty": "medium",
        "category": "guessthesong"
    },

          {
        "id": 579,
        "song": "Last friday night",
        "difficulty": "medium",
        "category": "guessthesong"
    },
         {
        "id": 580,
        "song": "Roar",
        "difficulty": "medium",
        "category": "guessthesong"
    },
         {
        "id": 581,
        "song": "Firework",
        "difficulty": "medium",
        "category": "guessthesong"
    },
         {
        "id": 582,
        "song": "Bang Bang",
        "difficulty": "medium",
        "category": "guessthesong"
    },
         {
        "id": 583,
        "song": "Bad Romance",
        "difficulty": "medium",
        "category": "guessthesong"
    },
         {
        "id": 584,
        "song": "I Took a Pill In Ibiza",
        "difficulty": "medium",
        "category": "guessthesong"
    },
         {
        "id": 585,
        "song": "Rain over me",
        "difficulty": "medium",
        "category": "guessthesong"
    },
         {
        "id": 586,
        "song": "Can't feel my face",
        "difficulty": "medium",
        "category": "guessthesong"
    },
         {
        "id": 587,
        "song": "Starboy",
        "difficulty": "medium",
        "category": "guessthesong"
    },
         {
        "id": 588,
        "song": "Cheerleader ",
        "difficulty": "medium",
        "category": "guessthesong"
    },
         {
        "id": 589,
        "song": "We Found Love",
        "difficulty": "medium",
        "category": "guessthesong"
    },
         {
        "id": 590,
        "song": "Focus",
        "difficulty": "medium",
        "category": "guessthesong"
    },
         {
        "id": 591,
        "song": "Titanium",
        "difficulty": "medium",
        "category": "guessthesong"
    },
         {
        "id": 592,
        "song": "Turn Down For What",
        "difficulty": "medium",
        "category": "guessthesong"
    },
         {
        "id": 593,
        "song": "Grenade",
        "difficulty": "medium",
        "category": "guessthesong"
    },
         {
        "id": 594,
        "song": "Give Me Everything",
        "difficulty": "medium",
        "category": "guessthesong"
    },
         {
        "id": 595,
        "song": "Party In The U.S.A.",
        "difficulty": "medium",
        "category": "guessthesong"
    },
         {
        "id": 596,
        "song": "Story of My Life",
        "difficulty": "medium",
        "category": "guessthesong"
    },
         {
        "id": 597,
        "song": "Hot N Cold",
        "difficulty": "medium",
        "category": "guessthesong"
    },
         {
        "id": 598,
        "song": "Price Tag",
        "difficulty": "medium",
        "category": "guessthesong"
    },
         {
        "id": 599,
        "song": "Russian Roulette",
        "difficulty": "medium",
        "category": "guessthesong"
    }

]
